pymempool/__init__.py
pymempool/_version.py
pymempool/api.py
pymempool/ascii_mempool_blocks.py
pymempool/block_parser.py
pymempool/cli.py
pymempool/difficulty_adjustment.py
pymempool/halving.py
pymempool/mempool_block_parser.py
pymempool/py.typed
pymempool/recommended_fees.py
pymempool/utils.py
pymempool/websocket.py
pymempool-0.2.1.dist-info/licenses/LICENSE
pymempool-0.2.1.dist-info/METADATA
pymempool-0.2.1.dist-info/WHEEL
pymempool-0.2.1.dist-info/entry_points.txt
pymempool-0.2.1.dist-info/top_level.txt
pymempool-0.2.1.dist-info/RECORD
