Metadata-Version: 2.4
Name: pymempool
Version: 0.2.1
Summary: Python Api for mempool.space
Author-email: Holger Nahrstaedt <nahrstaedt@gmail.com>
License: MIT License
Project-URL: Homepage, https://github.com/holgern/pymempool
Keywords: mempool,btc
Classifier: Intended Audience :: Developers
Classifier: License :: OSI Approved :: MIT License
Classifier: Operating System :: OS Independent
Classifier: Programming Language :: Python :: 3
Classifier: Programming Language :: Python :: 3.9
Classifier: Programming Language :: Python :: 3.10
Classifier: Programming Language :: Python :: 3.11
Classifier: Programming Language :: Python :: 3.12
Classifier: Topic :: Software Development :: Libraries
Requires-Python: >3.8.0
License-File: LICENSE
Requires-Dist: urllib3
Requires-Dist: typer
Requires-Dist: rich
Requires-Dist: requests
Requires-Dist: websockets
Dynamic: license-file
